asklora/README.md
asklora/__init__.py
asklora/brokerage/__init__.py
asklora/brokerage/client.py
asklora/brokerage/common.py
asklora/brokerage/enums.py
asklora/brokerage/exceptions.py
asklora/brokerage/ibkr.py
asklora/brokerage/iex.py
asklora/brokerage/logs.py
asklora/brokerage/models.py
asklora/brokerage/rest.py
asklora/brokerage/vars.py
asklora/dam.py
asklora/exceptions/__init__.py
asklora/exceptions/pgp.py
asklora/logger.py
asklora/pgp.py
asklora/portal.py
asklora/singleton.py
asklora/utils/__init__.py
asklora/utils/common.py
asklora/utils/file.py
asklora/utils/regexes.py
asklora_portal-1.1.13.dist-info/LICENSE
asklora_portal-1.1.13.dist-info/METADATA
asklora_portal-1.1.13.dist-info/WHEEL
asklora_portal-1.1.13.dist-info/RECORD
