Metadata-Version: 2.1
Name: asklora-portal
Version: 1.1.13
Summary: portal to use various api data service
License: MIT
Author: redloratech
Author-email: rede.akbar@loratechai.com
Requires-Python: >=3.9,<4.0
Classifier: License :: OSI Approved :: MIT License
Classifier: Programming Language :: Python :: 3
Classifier: Programming Language :: Python :: 3.9
Classifier: Programming Language :: Python :: 3.10
Classifier: Programming Language :: Python :: 3.11
Requires-Dist: pydantic-xml[lxml] (==1.0.0)
Requires-Dist: python-dateutil (>=2.8.2,<3.0.0)
Requires-Dist: python-dotenv (>=0.20.0,<0.21.0)
Requires-Dist: python-gnupg (>=0.5.0,<0.6.0)
Requires-Dist: requests (>=2.28.1,<3.0.0)
Requires-Dist: sseclient-py (>=1.7.2,<2.0.0)
Requires-Dist: structlog (>=22.3.0,<23.0.0)
